ExcelUtil/ExcelUtil.py
ExcelUtil/__init__.py
ExcelUtil/conf.py
Robot/ExcelUtil.py
Robot/__init__.py
Robot/conf.py
robotframework_excelutil-9.12.dist-info/LICENSE
robotframework_excelutil-9.12.dist-info/METADATA
robotframework_excelutil-9.12.dist-info/WHEEL
robotframework_excelutil-9.12.dist-info/top_level.txt
robotframework_excelutil-9.12.dist-info/RECORD
