Metadata-Version: 2.1
Name: robotframework-excelutil
Version: 9.12
Summary: Robotframework library for excel xlsx file format
Home-page: https://github.com/nagesh-bn/test1.git
Author: Nagesh B Nagaraja Rao
Author-email: nagesh.nagaraja@gmail.com
License: UNKNOWN
Platform: UNKNOWN
Requires-Dist: openpyxl
